prenacs/__init__.py
prenacs/attribute_definitions_manager.py
prenacs/batch_computation.py
prenacs/database.py
prenacs/formatting_helper.py
prenacs/plugin_interface_analyser.py
prenacs/plugins_helper.py
prenacs/report.py
prenacs/results_loader.py
prenacs/dbschema/__init__.py
prenacs/dbschema/attribute_definition.py
prenacs/dbschema/computation_report.py
prenacs/dbschema/plugin_description.py
prenacs/scripts_helpers/__init__.py
prenacs/scripts_helpers/common.py
prenacs/scripts_helpers/database.py
prenacs/scripts_helpers/report.py
prenacs-1.2.data/scripts/prenacs-batch-compute
prenacs-1.2.data/scripts/prenacs-check-plugin
prenacs-1.2.data/scripts/prenacs-create-attribute
prenacs-1.2.data/scripts/prenacs-drop-attribute
prenacs-1.2.data/scripts/prenacs-load-results
prenacs-1.2.data/scripts/prenacs-manage-attributes
prenacs-1.2.data/scripts/prenacs-setup-database
prenacs-1.2.dist-info/LICENSE.txt
prenacs-1.2.dist-info/METADATA
prenacs-1.2.dist-info/WHEEL
prenacs-1.2.dist-info/top_level.txt
prenacs-1.2.dist-info/RECORD
