Metadata-Version: 2.1
Name: prenacs
Version: 1.2
Summary: PRovenance-tracking ENtity "+                  "Attribute batch Computation and database Storage system
Home-page: https://github.com/ggonnella/prenacs
Author: Giorgio Gonnella
Author-email: gonnella@zbh.uni-hamburg.de
License: ISC
Keywords: batch computing,database,data provenance
Classifier: Development Status :: 5 - Production/Stable
Classifier: Environment :: Console
Classifier: Intended Audience :: Developers
Classifier: Intended Audience :: End Users/Desktop
Classifier: Intended Audience :: Science/Research
Classifier: License :: OSI Approved :: ISC License (ISCL)
Classifier: Operating System :: MacOS :: MacOS X
Classifier: Operating System :: POSIX :: Linux
Classifier: Programming Language :: Python :: 3 :: Only
Classifier: Topic :: Software Development :: Libraries
License-File: LICENSE.txt
Requires-Dist: sqlalchemy
Requires-Dist: sqlalchemy-repr
Requires-Dist: tqdm
Requires-Dist: schema
Requires-Dist: loguru
Requires-Dist: docopt
Requires-Dist: sh
Requires-Dist: dill
Requires-Dist: attrtables (==1.2)
Requires-Dist: multiplug (==1.2)
Requires-Dist: snacli (==1.2)
